knockknock/__init__.py
knockknock/__main__.py
knockknock/chime_sender.py
knockknock/desktop_sender.py
knockknock/dingtalk_sender.py
knockknock/discord_sender.py
knockknock/email_sender.py
knockknock/matrix_sender.py
knockknock/rocketchat_sender.py
knockknock/slack_sender.py
knockknock/sms_sender.py
knockknock/teams_sender.py
knockknock/telegram_sender.py
knockknock/wechat_sender.py
knockknock/tests/__init__.py
knockknock/tests/test_senders.py
knockknock-0.1.8.1.dist-info/LICENSE
knockknock-0.1.8.1.dist-info/METADATA
knockknock-0.1.8.1.dist-info/WHEEL
knockknock-0.1.8.1.dist-info/entry_points.txt
knockknock-0.1.8.1.dist-info/top_level.txt
knockknock-0.1.8.1.dist-info/RECORD
