Metadata-Version: 2.1
Name: knockknock
Version: 0.1.8.1
Summary: Be notified when your training is complete with only two additional lines of code
Home-page: http://github.com/huggingface/knockknock
Author: Victor SANH
Author-email: victorsanh@gmail.com
License: MIT
Platform: UNKNOWN
Classifier: Intended Audience :: Science/Research
Classifier: Development Status :: 3 - Alpha
Classifier: License :: OSI Approved :: MIT License
Classifier: Programming Language :: Python :: 3.6
Classifier: Topic :: Scientific/Engineering :: Artificial Intelligence
Requires-Python: >=3.6
Requires-Dist: yagmail (>=0.11.214)
Requires-Dist: keyring
Requires-Dist: matrix-client
Requires-Dist: python-telegram-bot
Requires-Dist: requests
Requires-Dist: twilio
